certbot_dns_isset/__init__.py
certbot_dns_isset/api.py
certbot_dns_isset/dns_isset.py
certbot_dns_isset/domain.py
certbot_dns_isset/record.py
certbot_dns_isset-0.0.3.dist-info/LICENSE
certbot_dns_isset-0.0.3.dist-info/METADATA
certbot_dns_isset-0.0.3.dist-info/WHEEL
certbot_dns_isset-0.0.3.dist-info/entry_points.txt
certbot_dns_isset-0.0.3.dist-info/top_level.txt
certbot_dns_isset-0.0.3.dist-info/RECORD
