Metadata-Version: 2.1
Name: certbot-dns-isset
Version: 0.0.3
Summary: Certbot plugin for Isset DNS
Home-page: http://isset.nl/
Author: Gerben Geijteman
Author-email: gerben@isset.nl
License: UNKNOWN
Platform: UNKNOWN
Classifier: Programming Language :: Python :: 3
Classifier: License :: OSI Approved :: MIT License
Classifier: Operating System :: OS Independent
Requires-Python: >=3.6
Requires-Dist: requests
Requires-Dist: certbot
Requires-Dist: zope.interface
